[
  {
    "id": "499761",
    "name": "### ROTANA LOW INTERNET ###",
    "url": "http://cf.business-cdn-8k.com/cf9b10a37c7c/f4bb9ed47c/499761.ts",
    "logo": "",
    "category": "AR| ROTANA LQ ▼ روتانا",
    "categoryId": "822",
    "epgId": "",
    "added": "1688818684",
    "type": "live"
  },
  {
    "id": "499760",
    "name": "AR: ROTANA CINEMA LQ",
    "url": "http://cf.business-cdn-8k.com/cf9b10a37c7c/f4bb9ed47c/499760.ts",
    "logo": "http://photo-tmdb.com/stalker_portal/misc/logos/320/48.jpg?59406",
    "category": "AR| ROTANA LQ ▼ روتانا",
    "categoryId": "822",
    "epgId": "RotanaCinema.eg",
    "added": "1688818684",
    "type": "live"
  },
  {
    "id": "499759",
    "name": "AR: ROTANA CLASSIC LQ",
    "url": "http://cf.business-cdn-8k.com/cf9b10a37c7c/f4bb9ed47c/499759.ts",
    "logo": "http://photo-tmdb.com/stalker_portal/misc/logos/320/47.jpg?34379",
    "category": "AR| ROTANA LQ ▼ روتانا",
    "categoryId": "822",
    "epgId": "RotanaClassic.eg",
    "added": "1688818684",
    "type": "live"
  },
  {
    "id": "499757",
    "name": "AR: ROTANA COMEDY LQ",
    "url": "http://cf.business-cdn-8k.com/cf9b10a37c7c/f4bb9ed47c/499757.ts",
    "logo": "http://photo-tmdb.com/stalker_portal/misc/logos/320/12790.jpg?85217",
    "category": "AR| ROTANA LQ ▼ روتانا",
    "categoryId": "822",
    "epgId": "",
    "added": "1688818684",
    "type": "live"
  },
  {
    "id": "499756",
    "name": "AR: ROTANA DRAMA LQ",
    "url": "http://cf.business-cdn-8k.com/cf9b10a37c7c/f4bb9ed47c/499756.ts",
    "logo": "http://photo-tmdb.com/stalker_portal/misc/logos/320/256.jpg?78257",
    "category": "AR| ROTANA LQ ▼ روتانا",
    "categoryId": "822",
    "epgId": "RotanaDramaAr.eg",
    "added": "1688818684",
    "type": "live"
  },
  {
    "id": "499754",
    "name": "AR: ROTANA MUSIC LQ",
    "url": "http://cf.business-cdn-8k.com/cf9b10a37c7c/f4bb9ed47c/499754.ts",
    "logo": "http://photo-tmdb.com/stalker_portal/misc/logos/320/46.jpg?43428",
    "category": "AR| ROTANA LQ ▼ روتانا",
    "categoryId": "822",
    "epgId": "RotanaMusic.eg",
    "added": "1688818684",
    "type": "live"
  },
  {
    "id": "499758",
    "name": "AR: ROTANA CLIP LQ",
    "url": "http://cf.business-cdn-8k.com/cf9b10a37c7c/f4bb9ed47c/499758.ts",
    "logo": "http://photo-tmdb.com/stalker_portal/misc/logos/320/255.jpg?97164",
    "category": "AR| ROTANA LQ ▼ روتانا",
    "categoryId": "822",
    "epgId": "",
    "added": "1688818684",
    "type": "live"
  },
  {
    "id": "499755",
    "name": "AR: ROTANA KHALIJEAH LQ",
    "url": "http://cf.business-cdn-8k.com/cf9b10a37c7c/f4bb9ed47c/499755.ts",
    "logo": "http://photo-tmdb.com/stalker_portal/misc/logos/320/258.jpg?68899",
    "category": "AR| ROTANA LQ ▼ روتانا",
    "categoryId": "822",
    "epgId": "RotanaKhalijiah.eg",
    "added": "1688818684",
    "type": "live"
  },
  {
    "id": "499753",
    "name": "AR: RESSALA LQ",
    "url": "http://cf.business-cdn-8k.com/cf9b10a37c7c/f4bb9ed47c/499753.ts",
    "logo": "http://photo-tmdb.com/stalker_portal/misc/logos/320/50.jpg?85713",
    "category": "AR| ROTANA LQ ▼ روتانا",
    "categoryId": "822",
    "epgId": "",
    "added": "1688818684",
    "type": "live"
  }
]