[
  {
    "tvgId": "GOBX",
    "name": "####### GOBX ᴴᴰ #######",
    "originalName": "####### GOBX ᴴᴰ #######",
    "url": "http://cf.business-cdn-8k.com/cf9b10a37c7c/f4bb9ed47c/1353220.ts",
    "logo": "",
    "category": "Ar| Gobx ᴮᴱ",
    "originalCategory": "AR| GOBX ᴮᴱ",
    "country": "",
    "type": "live",
    "source": "xtream"
  },
  {
    "tvgId": "GOBXMBCELIFE.be",
    "name": "GOBX MBC ELIFE ᴴᴰ",
    "originalName": "BE: GOBX MBC ELIFE ᴴᴰ",
    "url": "http://cf.business-cdn-8k.com/cf9b10a37c7c/f4bb9ed47c/1353219.ts",
    "logo": "http://photo-tmdb.com/stalker_portal/misc/logos/320/13334.jpg?59189",
    "category": "Ar| Gobx ᴮᴱ",
    "originalCategory": "AR| GOBX ᴮᴱ",
    "country": "BE",
    "type": "live",
    "source": "xtream"
  },
  {
    "tvgId": "GOBXMBC1.be",
    "name": "GOBX MBC 1 ᴴᴰ",
    "originalName": "BE: GOBX MBC 1 ᴴᴰ",
    "url": "http://cf.business-cdn-8k.com/cf9b10a37c7c/f4bb9ed47c/1353218.ts",
    "logo": "http://photo-tmdb.com/stalker_portal/misc/logos/320/13334.jpg?59189",
    "category": "Ar| Gobx ᴮᴱ",
    "originalCategory": "AR| GOBX ᴮᴱ",
    "country": "BE",
    "type": "live",
    "source": "xtream"
  },
  {
    "tvgId": "GOBXMBC2.be",
    "name": "GOBX MBC 2 ᴴᴰ",
    "originalName": "BE: GOBX MBC 2 ᴴᴰ",
    "url": "http://cf.business-cdn-8k.com/cf9b10a37c7c/f4bb9ed47c/1353217.ts",
    "logo": "http://photo-tmdb.com/stalker_portal/misc/logos/320/13334.jpg?59189",
    "category": "Ar| Gobx ᴮᴱ",
    "originalCategory": "AR| GOBX ᴮᴱ",
    "country": "BE",
    "type": "live",
    "source": "xtream"
  },
  {
    "tvgId": "GOBXMBC3.be",
    "name": "GOBX MBC 3 ᴴᴰ",
    "originalName": "BE: GOBX MBC 3 ᴴᴰ",
    "url": "http://cf.business-cdn-8k.com/cf9b10a37c7c/f4bb9ed47c/1353216.ts",
    "logo": "http://photo-tmdb.com/stalker_portal/misc/logos/320/13334.jpg?59189",
    "category": "Ar| Gobx ᴮᴱ",
    "originalCategory": "AR| GOBX ᴮᴱ",
    "country": "BE",
    "type": "live",
    "source": "xtream"
  },
  {
    "tvgId": "GOBXMBC4.be",
    "name": "GOBX MBC 4 ᴴᴰ",
    "originalName": "BE: GOBX MBC 4 ᴴᴰ",
    "url": "http://cf.business-cdn-8k.com/cf9b10a37c7c/f4bb9ed47c/1353215.ts",
    "logo": "http://photo-tmdb.com/stalker_portal/misc/logos/320/13334.jpg?59189",
    "category": "Ar| Gobx ᴮᴱ",
    "originalCategory": "AR| GOBX ᴮᴱ",
    "country": "BE",
    "type": "live",
    "source": "xtream"
  },
  {
    "tvgId": "GOBXMBC5.be",
    "name": "GOBX MBC 5 ᴴᴰ",
    "originalName": "BE: GOBX MBC 5 ᴴᴰ",
    "url": "http://cf.business-cdn-8k.com/cf9b10a37c7c/f4bb9ed47c/1353214.ts",
    "logo": "http://photo-tmdb.com/stalker_portal/misc/logos/320/13334.jpg?59189",
    "category": "Ar| Gobx ᴮᴱ",
    "originalCategory": "AR| GOBX ᴮᴱ",
    "country": "BE",
    "type": "live",
    "source": "xtream"
  },
  {
    "tvgId": "GOBXMBCDRAMA.be",
    "name": "GOBX MBC DRAMA ᴴᴰ",
    "originalName": "BE: GOBX MBC DRAMA ᴴᴰ",
    "url": "http://cf.business-cdn-8k.com/cf9b10a37c7c/f4bb9ed47c/1353213.ts",
    "logo": "http://photo-tmdb.com/stalker_portal/misc/logos/320/13334.jpg?59189",
    "category": "Ar| Gobx ᴮᴱ",
    "originalCategory": "AR| GOBX ᴮᴱ",
    "country": "BE",
    "type": "live",
    "source": "xtream"
  },
  {
    "tvgId": "GOBXMBCACTION.be",
    "name": "GOBX MBC ACTION ᴴᴰ",
    "originalName": "BE: GOBX MBC ACTION ᴴᴰ",
    "url": "http://cf.business-cdn-8k.com/cf9b10a37c7c/f4bb9ed47c/1353212.ts",
    "logo": "http://photo-tmdb.com/stalker_portal/misc/logos/320/13334.jpg?59189",
    "category": "Ar| Gobx ᴮᴱ",
    "originalCategory": "AR| GOBX ᴮᴱ",
    "country": "BE",
    "type": "live",
    "source": "xtream"
  },
  {
    "tvgId": "GOBXMBCMASR1.be",
    "name": "GOBX MBC MASR 1 ᴴᴰ",
    "originalName": "BE: GOBX MBC MASR 1 ᴴᴰ",
    "url": "http://cf.business-cdn-8k.com/cf9b10a37c7c/f4bb9ed47c/1353211.ts",
    "logo": "http://photo-tmdb.com/stalker_portal/misc/logos/320/13334.jpg?59189",
    "category": "Ar| Gobx ᴮᴱ",
    "originalCategory": "AR| GOBX ᴮᴱ",
    "country": "BE",
    "type": "live",
    "source": "xtream"
  },
  {
    "tvgId": "GOBXMBCMASR2.be",
    "name": "GOBX MBC MASR 2 ᴴᴰ",
    "originalName": "BE: GOBX MBC MASR 2 ᴴᴰ",
    "url": "http://cf.business-cdn-8k.com/cf9b10a37c7c/f4bb9ed47c/1353210.ts",
    "logo": "http://photo-tmdb.com/stalker_portal/misc/logos/320/13334.jpg?59189",
    "category": "Ar| Gobx ᴮᴱ",
    "originalCategory": "AR| GOBX ᴮᴱ",
    "country": "BE",
    "type": "live",
    "source": "xtream"
  },
  {
    "tvgId": "GOBXMBCIRAQ.be",
    "name": "GOBX MBC IRAQ ᴴᴰ",
    "originalName": "BE: GOBX MBC IRAQ ᴴᴰ",
    "url": "http://cf.business-cdn-8k.com/cf9b10a37c7c/f4bb9ed47c/1353209.ts",
    "logo": "http://photo-tmdb.com/stalker_portal/misc/logos/320/13334.jpg?59189",
    "category": "Ar| Gobx ᴮᴱ",
    "originalCategory": "AR| GOBX ᴮᴱ",
    "country": "BE",
    "type": "live",
    "source": "xtream"
  },
  {
    "tvgId": "GOBXMBCDRAMA.be",
    "name": "GOBX MBC DRAMA+ ᴴᴰ",
    "originalName": "BE: GOBX MBC DRAMA+ ᴴᴰ",
    "url": "http://cf.business-cdn-8k.com/cf9b10a37c7c/f4bb9ed47c/1353208.ts",
    "logo": "http://photo-tmdb.com/stalker_portal/misc/logos/320/13334.jpg?59189",
    "category": "Ar| Gobx ᴮᴱ",
    "originalCategory": "AR| GOBX ᴮᴱ",
    "country": "BE",
    "type": "live",
    "source": "xtream"
  },
  {
    "tvgId": "GOBXMBCVARIETY.be",
    "name": "GOBX MBC VARIETY ᴴᴰ",
    "originalName": "BE: GOBX MBC VARIETY ᴴᴰ",
    "url": "http://cf.business-cdn-8k.com/cf9b10a37c7c/f4bb9ed47c/1353207.ts",
    "logo": "http://photo-tmdb.com/stalker_portal/misc/logos/320/13334.jpg?59189",
    "category": "Ar| Gobx ᴮᴱ",
    "originalCategory": "AR| GOBX ᴮᴱ",
    "country": "BE",
    "type": "live",
    "source": "xtream"
  },
  {
    "tvgId": "GOBXMBCMAX.be",
    "name": "GOBX MBC MAX ᴴᴰ",
    "originalName": "BE: GOBX MBC MAX ᴴᴰ",
    "url": "http://cf.business-cdn-8k.com/cf9b10a37c7c/f4bb9ed47c/1353206.ts",
    "logo": "http://photo-tmdb.com/stalker_portal/misc/logos/320/13334.jpg?59189",
    "category": "Ar| Gobx ᴮᴱ",
    "originalCategory": "AR| GOBX ᴮᴱ",
    "country": "BE",
    "type": "live",
    "source": "xtream"
  },
  {
    "tvgId": "GOBXMBCFM.be",
    "name": "GOBX MBC FM ᴴᴰ",
    "originalName": "BE: GOBX MBC FM ᴴᴰ",
    "url": "http://cf.business-cdn-8k.com/cf9b10a37c7c/f4bb9ed47c/1353205.ts",
    "logo": "http://photo-tmdb.com/stalker_portal/misc/logos/320/13334.jpg?59189",
    "category": "Ar| Gobx ᴮᴱ",
    "originalCategory": "AR| GOBX ᴮᴱ",
    "country": "BE",
    "type": "live",
    "source": "xtream"
  },
  {
    "tvgId": "GOBXMBCPERSIA.be",
    "name": "GOBX MBC PERSIA ᴴᴰ",
    "originalName": "BE: GOBX MBC PERSIA ᴴᴰ",
    "url": "http://cf.business-cdn-8k.com/cf9b10a37c7c/f4bb9ed47c/1353204.ts",
    "logo": "http://photo-tmdb.com/stalker_portal/misc/logos/320/13334.jpg?59189",
    "category": "Ar| Gobx ᴮᴱ",
    "originalCategory": "AR| GOBX ᴮᴱ",
    "country": "BE",
    "type": "live",
    "source": "xtream"
  },
  {
    "tvgId": "GOBXMBCGAMING.be",
    "name": "GOBX MBC GAMING ᴴᴰ",
    "originalName": "BE: GOBX MBC GAMING ᴴᴰ",
    "url": "http://cf.business-cdn-8k.com/cf9b10a37c7c/f4bb9ed47c/1353203.ts",
    "logo": "http://photo-tmdb.com/stalker_portal/misc/logos/320/13334.jpg?59189",
    "category": "Ar| Gobx ᴮᴱ",
    "originalCategory": "AR| GOBX ᴮᴱ",
    "country": "BE",
    "type": "live",
    "source": "xtream"
  },
  {
    "tvgId": "GOBXROTANAAFLAM.be",
    "name": "GOBX ROTANA AFLAM+ ᴴᴰ",
    "originalName": "BE: GOBX ROTANA AFLAM+ ᴴᴰ",
    "url": "http://cf.business-cdn-8k.com/cf9b10a37c7c/f4bb9ed47c/1353202.ts",
    "logo": "http://photo-tmdb.com/stalker_portal/misc/logos/320/13334.jpg?59189",
    "category": "Ar| Gobx ᴮᴱ",
    "originalCategory": "AR| GOBX ᴮᴱ",
    "country": "BE",
    "type": "live",
    "source": "xtream"
  },
  {
    "tvgId": "GOBXROTANAM.be",
    "name": "GOBX ROTANA M+ ᴴᴰ",
    "originalName": "BE: GOBX ROTANA M+ ᴴᴰ",
    "url": "http://cf.business-cdn-8k.com/cf9b10a37c7c/f4bb9ed47c/1353201.ts",
    "logo": "http://photo-tmdb.com/stalker_portal/misc/logos/320/13334.jpg?59189",
    "category": "Ar| Gobx ᴮᴱ",
    "originalCategory": "AR| GOBX ᴮᴱ",
    "country": "BE",
    "type": "live",
    "source": "xtream"
  },
  {
    "tvgId": "GOBXROTANAKIDS.be",
    "name": "GOBX ROTANA KIDS ᴴᴰ",
    "originalName": "BE: GOBX ROTANA KIDS ᴴᴰ",
    "url": "http://cf.business-cdn-8k.com/cf9b10a37c7c/f4bb9ed47c/1353200.ts",
    "logo": "http://photo-tmdb.com/stalker_portal/misc/logos/320/13334.jpg?59189",
    "category": "Ar| Gobx ᴮᴱ",
    "originalCategory": "AR| GOBX ᴮᴱ",
    "country": "BE",
    "type": "live",
    "source": "xtream"
  },
  {
    "tvgId": "GOBXROTANA.be",
    "name": "GOBX ROTANA+ ᴴᴰ",
    "originalName": "BE: GOBX ROTANA+ ᴴᴰ",
    "url": "http://cf.business-cdn-8k.com/cf9b10a37c7c/f4bb9ed47c/1353199.ts",
    "logo": "http://photo-tmdb.com/stalker_portal/misc/logos/320/13334.jpg?59189",
    "category": "Ar| Gobx ᴮᴱ",
    "originalCategory": "AR| GOBX ᴮᴱ",
    "country": "BE",
    "type": "live",
    "source": "xtream"
  },
  {
    "tvgId": "GOBXROTANACINEMAUS.be",
    "name": "GOBX ROTANA CINEMA +US ᴴᴰ",
    "originalName": "BE: GOBX ROTANA CINEMA +US ᴴᴰ",
    "url": "http://cf.business-cdn-8k.com/cf9b10a37c7c/f4bb9ed47c/1353198.ts",
    "logo": "http://photo-tmdb.com/stalker_portal/misc/logos/320/13334.jpg?59189",
    "category": "Ar| Gobx ᴮᴱ",
    "originalCategory": "AR| GOBX ᴮᴱ",
    "country": "BE",
    "type": "live",
    "source": "xtream"
  },
  {
    "tvgId": "GOBXROTANACINEMAFR.be",
    "name": "GOBX ROTANA CINEMA +FR ᴴᴰ",
    "originalName": "BE: GOBX ROTANA CINEMA +FR ᴴᴰ",
    "url": "http://cf.business-cdn-8k.com/cf9b10a37c7c/f4bb9ed47c/1353197.ts",
    "logo": "http://photo-tmdb.com/stalker_portal/misc/logos/320/13334.jpg?59189",
    "category": "Ar| Gobx ᴮᴱ",
    "originalCategory": "AR| GOBX ᴮᴱ",
    "country": "BE",
    "type": "live",
    "source": "xtream"
  },
  {
    "tvgId": "GOBXDISENY.be",
    "name": "GOBX DISENY ᴴᴰ",
    "originalName": "BE: GOBX DISENY ᴴᴰ",
    "url": "http://cf.business-cdn-8k.com/cf9b10a37c7c/f4bb9ed47c/1353196.ts",
    "logo": "http://photo-tmdb.com/stalker_portal/misc/logos/320/13334.jpg?59189",
    "category": "Ar| Gobx ᴮᴱ",
    "originalCategory": "AR| GOBX ᴮᴱ",
    "country": "BE",
    "type": "live",
    "source": "xtream"
  },
  {
    "tvgId": "GOBXDISENYJR.be",
    "name": "GOBX DISENY JR ᴴᴰ",
    "originalName": "BE: GOBX DISENY JR ᴴᴰ",
    "url": "http://cf.business-cdn-8k.com/cf9b10a37c7c/f4bb9ed47c/1353195.ts",
    "logo": "http://photo-tmdb.com/stalker_portal/misc/logos/320/13334.jpg?59189",
    "category": "Ar| Gobx ᴮᴱ",
    "originalCategory": "AR| GOBX ᴮᴱ",
    "country": "BE",
    "type": "live",
    "source": "xtream"
  },
  {
    "tvgId": "GOBXSTCSPORT1.be",
    "name": "GOBX STC SPORT 1 ᴴᴰ",
    "originalName": "BE: GOBX STC SPORT 1 ᴴᴰ",
    "url": "http://cf.business-cdn-8k.com/cf9b10a37c7c/f4bb9ed47c/1353194.ts",
    "logo": "http://photo-tmdb.com/stalker_portal/misc/logos/320/13334.jpg?59189",
    "category": "Ar| Gobx ᴮᴱ",
    "originalCategory": "AR| GOBX ᴮᴱ",
    "country": "BE",
    "type": "live",
    "source": "xtream"
  },
  {
    "tvgId": "GOBXSTCSPORT2.be",
    "name": "GOBX STC SPORT 2 ᴴᴰ",
    "originalName": "BE: GOBX STC SPORT 2 ᴴᴰ",
    "url": "http://cf.business-cdn-8k.com/cf9b10a37c7c/f4bb9ed47c/1353193.ts",
    "logo": "http://photo-tmdb.com/stalker_portal/misc/logos/320/13334.jpg?59189",
    "category": "Ar| Gobx ᴮᴱ",
    "originalCategory": "AR| GOBX ᴮᴱ",
    "country": "BE",
    "type": "live",
    "source": "xtream"
  },
  {
    "tvgId": "GOBXSTCTVCINEMA.be",
    "name": "GOBX STC TV CINEMA ᴴᴰ",
    "originalName": "BE: GOBX STC TV CINEMA ᴴᴰ",
    "url": "http://cf.business-cdn-8k.com/cf9b10a37c7c/f4bb9ed47c/1353192.ts",
    "logo": "http://photo-tmdb.com/stalker_portal/misc/logos/320/13334.jpg?59189",
    "category": "Ar| Gobx ᴮᴱ",
    "originalCategory": "AR| GOBX ᴮᴱ",
    "country": "BE",
    "type": "live",
    "source": "xtream"
  },
  {
    "tvgId": "GOBXSTCFAMILY.be",
    "name": "GOBX STC FAMILY ᴴᴰ",
    "originalName": "BE: GOBX STC FAMILY ᴴᴰ",
    "url": "http://cf.business-cdn-8k.com/cf9b10a37c7c/f4bb9ed47c/1353191.ts",
    "logo": "http://photo-tmdb.com/stalker_portal/misc/logos/320/13334.jpg?59189",
    "category": "Ar| Gobx ᴮᴱ",
    "originalCategory": "AR| GOBX ᴮᴱ",
    "country": "BE",
    "type": "live",
    "source": "xtream"
  },
  {
    "tvgId": "GOBXSTCDRAMA.be",
    "name": "GOBX STC DRAMA ᴴᴰ",
    "originalName": "BE: GOBX STC DRAMA ᴴᴰ",
    "url": "http://cf.business-cdn-8k.com/cf9b10a37c7c/f4bb9ed47c/1353190.ts",
    "logo": "http://photo-tmdb.com/stalker_portal/misc/logos/320/13334.jpg?59189",
    "category": "Ar| Gobx ᴮᴱ",
    "originalCategory": "AR| GOBX ᴮᴱ",
    "country": "BE",
    "type": "live",
    "source": "xtream"
  },
  {
    "tvgId": "GOBXNATURETIME.be",
    "name": "GOBX NATURE TIME ᴴᴰ",
    "originalName": "BE: GOBX NATURE TIME ᴴᴰ",
    "url": "http://cf.business-cdn-8k.com/cf9b10a37c7c/f4bb9ed47c/1353189.ts",
    "logo": "http://photo-tmdb.com/stalker_portal/misc/logos/320/13334.jpg?59189",
    "category": "Ar| Gobx ᴮᴱ",
    "originalCategory": "AR| GOBX ᴮᴱ",
    "country": "BE",
    "type": "live",
    "source": "xtream"
  },
  {
    "tvgId": "GOBXTIJI.be",
    "name": "GOBX TIJI ᴴᴰ",
    "originalName": "BE: GOBX TIJI ᴴᴰ",
    "url": "http://cf.business-cdn-8k.com/cf9b10a37c7c/f4bb9ed47c/1353188.ts",
    "logo": "http://photo-tmdb.com/stalker_portal/misc/logos/320/13334.jpg?59189",
    "category": "Ar| Gobx ᴮᴱ",
    "originalCategory": "AR| GOBX ᴮᴱ",
    "country": "BE",
    "type": "live",
    "source": "xtream"
  },
  {
    "tvgId": "GOBXGULIBILARABIC.be",
    "name": "GOBX GULI BIL ARABIC ᴴᴰ",
    "originalName": "BE: GOBX GULI BIL ARABIC ᴴᴰ",
    "url": "http://cf.business-cdn-8k.com/cf9b10a37c7c/f4bb9ed47c/1353187.ts",
    "logo": "http://photo-tmdb.com/stalker_portal/misc/logos/320/13334.jpg?59189",
    "category": "Ar| Gobx ᴮᴱ",
    "originalCategory": "AR| GOBX ᴮᴱ",
    "country": "BE",
    "type": "live",
    "source": "xtream"
  },
  {
    "tvgId": "GOBXALLIQAAMINALSIFR.be",
    "name": "GOBX AL LIQAA MIN AL SIFR ᴴᴰ",
    "originalName": "BE: GOBX AL LIQAA MIN AL SIFR ᴴᴰ",
    "url": "http://cf.business-cdn-8k.com/cf9b10a37c7c/f4bb9ed47c/1353186.ts",
    "logo": "http://photo-tmdb.com/stalker_portal/misc/logos/320/13334.jpg?59189",
    "category": "Ar| Gobx ᴮᴱ",
    "originalCategory": "AR| GOBX ᴮᴱ",
    "country": "BE",
    "type": "live",
    "source": "xtream"
  },
  {
    "tvgId": "GOBXASILIWAHASRI.be",
    "name": "GOBX ASILI WAHASRI ᴴᴰ",
    "originalName": "BE: GOBX ASILI WAHASRI ᴴᴰ",
    "url": "http://cf.business-cdn-8k.com/cf9b10a37c7c/f4bb9ed47c/1353185.ts",
    "logo": "http://photo-tmdb.com/stalker_portal/misc/logos/320/13334.jpg?59189",
    "category": "Ar| Gobx ᴮᴱ",
    "originalCategory": "AR| GOBX ᴮᴱ",
    "country": "BE",
    "type": "live",
    "source": "xtream"
  },
  {
    "tvgId": "GOBXFIGHTNETWORK.be",
    "name": "GOBX FIGHT NETWORK ᴴᴰ",
    "originalName": "BE: GOBX FIGHT NETWORK ᴴᴰ",
    "url": "http://cf.business-cdn-8k.com/cf9b10a37c7c/f4bb9ed47c/1353184.ts",
    "logo": "http://photo-tmdb.com/stalker_portal/misc/logos/320/13334.jpg?59189",
    "category": "Ar| Gobx ᴮᴱ",
    "originalCategory": "AR| GOBX ᴮᴱ",
    "country": "BE",
    "type": "live",
    "source": "xtream"
  },
  {
    "tvgId": "GOBXDAZANNASSR.be",
    "name": "GOBX DAZAN NASSR ᴴᴰ",
    "originalName": "BE: GOBX DAZAN NASSR ᴴᴰ",
    "url": "http://cf.business-cdn-8k.com/cf9b10a37c7c/f4bb9ed47c/1353183.ts",
    "logo": "http://photo-tmdb.com/stalker_portal/misc/logos/320/13334.jpg?59189",
    "category": "Ar| Gobx ᴮᴱ",
    "originalCategory": "AR| GOBX ᴮᴱ",
    "country": "BE",
    "type": "live",
    "source": "xtream"
  },
  {
    "tvgId": "GOBXARABSGOTTALENT.be",
    "name": "GOBX ARABS GOT TALENT ᴴᴰ",
    "originalName": "BE: GOBX ARABS GOT TALENT ᴴᴰ",
    "url": "http://cf.business-cdn-8k.com/cf9b10a37c7c/f4bb9ed47c/1353182.ts",
    "logo": "http://photo-tmdb.com/stalker_portal/misc/logos/320/13334.jpg?59189",
    "category": "Ar| Gobx ᴮᴱ",
    "originalCategory": "AR| GOBX ᴮᴱ",
    "country": "BE",
    "type": "live",
    "source": "xtream"
  },
  {
    "tvgId": "GOBXDRAMATURKEY.be",
    "name": "GOBX DRAMA TURKEY ᴴᴰ",
    "originalName": "BE: GOBX DRAMA TURKEY ᴴᴰ",
    "url": "http://cf.business-cdn-8k.com/cf9b10a37c7c/f4bb9ed47c/1353181.ts",
    "logo": "http://photo-tmdb.com/stalker_portal/misc/logos/320/13334.jpg?59189",
    "category": "Ar| Gobx ᴮᴱ",
    "originalCategory": "AR| GOBX ᴮᴱ",
    "country": "BE",
    "type": "live",
    "source": "xtream"
  },
  {
    "tvgId": "GOBXZOOMOO.be",
    "name": "GOBX ZOOMOO ᴴᴰ",
    "originalName": "BE: GOBX ZOOMOO ᴴᴰ",
    "url": "http://cf.business-cdn-8k.com/cf9b10a37c7c/f4bb9ed47c/1353180.ts",
    "logo": "http://photo-tmdb.com/stalker_portal/misc/logos/320/13334.jpg?59189",
    "category": "Ar| Gobx ᴮᴱ",
    "originalCategory": "AR| GOBX ᴮᴱ",
    "country": "BE",
    "type": "live",
    "source": "xtream"
  },
  {
    "tvgId": "GOBXMOTORVISION.be",
    "name": "GOBX MOTORVISION ᴴᴰ",
    "originalName": "BE: GOBX MOTORVISION ᴴᴰ",
    "url": "http://cf.business-cdn-8k.com/cf9b10a37c7c/f4bb9ed47c/1353179.ts",
    "logo": "http://photo-tmdb.com/stalker_portal/misc/logos/320/13334.jpg?59189",
    "category": "Ar| Gobx ᴮᴱ",
    "originalCategory": "AR| GOBX ᴮᴱ",
    "country": "BE",
    "type": "live",
    "source": "xtream"
  },
  {
    "tvgId": "GOBXTHAQAFEYYAH.be",
    "name": "GOBX THAQAFEYYAH ᴴᴰ",
    "originalName": "BE: GOBX THAQAFEYYAH ᴴᴰ",
    "url": "http://cf.business-cdn-8k.com/cf9b10a37c7c/f4bb9ed47c/1353178.ts",
    "logo": "http://photo-tmdb.com/stalker_portal/misc/logos/320/13334.jpg?59189",
    "category": "Ar| Gobx ᴮᴱ",
    "originalCategory": "AR| GOBX ᴮᴱ",
    "country": "BE",
    "type": "live",
    "source": "xtream"
  },
  {
    "tvgId": "GOBXTRACEURBAN.be",
    "name": "GOBX TRACE URBAN ᴴᴰ",
    "originalName": "BE: GOBX TRACE URBAN ᴴᴰ",
    "url": "http://cf.business-cdn-8k.com/cf9b10a37c7c/f4bb9ed47c/1353177.ts",
    "logo": "http://photo-tmdb.com/stalker_portal/misc/logos/320/13334.jpg?59189",
    "category": "Ar| Gobx ᴮᴱ",
    "originalCategory": "AR| GOBX ᴮᴱ",
    "country": "BE",
    "type": "live",
    "source": "xtream"
  },
  {
    "tvgId": "GOBXTRACESPORTSTARS.be",
    "name": "GOBX TRACE SPORT STARS ᴴᴰ",
    "originalName": "BE: GOBX TRACE SPORT STARS ᴴᴰ",
    "url": "http://cf.business-cdn-8k.com/cf9b10a37c7c/f4bb9ed47c/1353176.ts",
    "logo": "http://photo-tmdb.com/stalker_portal/misc/logos/320/13334.jpg?59189",
    "category": "Ar| Gobx ᴮᴱ",
    "originalCategory": "AR| GOBX ᴮᴱ",
    "country": "BE",
    "type": "live",
    "source": "xtream"
  },
  {
    "tvgId": "GOBXASHARQDOCUMENTARY.be",
    "name": "GOBX ASHARQ DOCUMENTARY ᴴᴰ",
    "originalName": "BE: GOBX ASHARQ DOCUMENTARY ᴴᴰ",
    "url": "http://cf.business-cdn-8k.com/cf9b10a37c7c/f4bb9ed47c/1353175.ts",
    "logo": "http://photo-tmdb.com/stalker_portal/misc/logos/320/13334.jpg?59189",
    "category": "Ar| Gobx ᴮᴱ",
    "originalCategory": "AR| GOBX ᴮᴱ",
    "country": "BE",
    "type": "live",
    "source": "xtream"
  },
  {
    "tvgId": "GOBXFASHIONTV.be",
    "name": "GOBX FASHION TV ᴴᴰ",
    "originalName": "BE: GOBX FASHION TV ᴴᴰ",
    "url": "http://cf.business-cdn-8k.com/cf9b10a37c7c/f4bb9ed47c/1353174.ts",
    "logo": "http://photo-tmdb.com/stalker_portal/misc/logos/320/13334.jpg?59189",
    "category": "Ar| Gobx ᴮᴱ",
    "originalCategory": "AR| GOBX ᴮᴱ",
    "country": "BE",
    "type": "live",
    "source": "xtream"
  },
  {
    "tvgId": "GOBXHORSE.be",
    "name": "GOBX HORSE ᴴᴰ",
    "originalName": "BE: GOBX HORSE ᴴᴰ",
    "url": "http://cf.business-cdn-8k.com/cf9b10a37c7c/f4bb9ed47c/1353173.ts",
    "logo": "http://photo-tmdb.com/stalker_portal/misc/logos/320/13334.jpg?59189",
    "category": "Ar| Gobx ᴮᴱ",
    "originalCategory": "AR| GOBX ᴮᴱ",
    "country": "BE",
    "type": "live",
    "source": "xtream"
  },
  {
    "tvgId": "GOBXINSIGHTTV.be",
    "name": "GOBX INSIGHTTV ᴴᴰ",
    "originalName": "BE: GOBX INSIGHTTV ᴴᴰ",
    "url": "http://cf.business-cdn-8k.com/cf9b10a37c7c/f4bb9ed47c/1353172.ts",
    "logo": "http://photo-tmdb.com/stalker_portal/misc/logos/320/13334.jpg?59189",
    "category": "Ar| Gobx ᴮᴱ",
    "originalCategory": "AR| GOBX ᴮᴱ",
    "country": "BE",
    "type": "live",
    "source": "xtream"
  },
  {
    "tvgId": "GOBXTHEKHAYAL.be",
    "name": "GOBX THEKHAYAL ᴴᴰ",
    "originalName": "BE: GOBX THEKHAYAL ᴴᴰ",
    "url": "http://cf.business-cdn-8k.com/cf9b10a37c7c/f4bb9ed47c/1353171.ts",
    "logo": "http://photo-tmdb.com/stalker_portal/misc/logos/320/13334.jpg?59189",
    "category": "Ar| Gobx ᴮᴱ",
    "originalCategory": "AR| GOBX ᴮᴱ",
    "country": "BE",
    "type": "live",
    "source": "xtream"
  },
  {
    "tvgId": "GOBXBIGWORLD.be",
    "name": "GOBX BIG WORLD ᴴᴰ",
    "originalName": "BE: GOBX BIG WORLD ᴴᴰ",
    "url": "http://cf.business-cdn-8k.com/cf9b10a37c7c/f4bb9ed47c/1353170.ts",
    "logo": "http://photo-tmdb.com/stalker_portal/misc/logos/320/13334.jpg?59189",
    "category": "Ar| Gobx ᴮᴱ",
    "originalCategory": "AR| GOBX ᴮᴱ",
    "country": "BE",
    "type": "live",
    "source": "xtream"
  },
  {
    "tvgId": "GOBXREDBULLTV.be",
    "name": "GOBX RED BULL TV ᴴᴰ",
    "originalName": "BE: GOBX RED BULL TV ᴴᴰ",
    "url": "http://cf.business-cdn-8k.com/cf9b10a37c7c/f4bb9ed47c/1353169.ts",
    "logo": "http://photo-tmdb.com/stalker_portal/misc/logos/320/13334.jpg?59189",
    "category": "Ar| Gobx ᴮᴱ",
    "originalCategory": "AR| GOBX ᴮᴱ",
    "country": "BE",
    "type": "live",
    "source": "xtream"
  },
  {
    "tvgId": "GOBXADB.be",
    "name": "GOBX ADB ᴴᴰ",
    "originalName": "BE: GOBX ADB ᴴᴰ",
    "url": "http://cf.business-cdn-8k.com/cf9b10a37c7c/f4bb9ed47c/1353168.ts",
    "logo": "http://photo-tmdb.com/stalker_portal/misc/logos/320/13334.jpg?59189",
    "category": "Ar| Gobx ᴮᴱ",
    "originalCategory": "AR| GOBX ᴮᴱ",
    "country": "BE",
    "type": "live",
    "source": "xtream"
  },
  {
    "tvgId": "GOBX24SPORTKSA.be",
    "name": "GOBX 24 SPORT KSA ᴴᴰ",
    "originalName": "BE: GOBX 24 SPORT KSA ᴴᴰ",
    "url": "http://cf.business-cdn-8k.com/cf9b10a37c7c/f4bb9ed47c/1353167.ts",
    "logo": "http://photo-tmdb.com/stalker_portal/misc/logos/320/13334.jpg?59189",
    "category": "Ar| Gobx ᴮᴱ",
    "originalCategory": "AR| GOBX ᴮᴱ",
    "country": "BE",
    "type": "live",
    "source": "xtream"
  },
  {
    "tvgId": "GOBXSMARTZONE.be",
    "name": "GOBX SMART ZONE ᴴᴰ",
    "originalName": "BE: GOBX SMART ZONE ᴴᴰ",
    "url": "http://cf.business-cdn-8k.com/cf9b10a37c7c/f4bb9ed47c/1353166.ts",
    "logo": "http://photo-tmdb.com/stalker_portal/misc/logos/320/13334.jpg?59189",
    "category": "Ar| Gobx ᴮᴱ",
    "originalCategory": "AR| GOBX ᴮᴱ",
    "country": "BE",
    "type": "live",
    "source": "xtream"
  },
  {
    "tvgId": "GOBXKIDZZONEMAX.be",
    "name": "GOBX KIDZ ZONE MAX ᴴᴰ",
    "originalName": "BE: GOBX KIDZ ZONE MAX ᴴᴰ",
    "url": "http://cf.business-cdn-8k.com/cf9b10a37c7c/f4bb9ed47c/1353165.ts",
    "logo": "http://photo-tmdb.com/stalker_portal/misc/logos/320/13334.jpg?59189",
    "category": "Ar| Gobx ᴮᴱ",
    "originalCategory": "AR| GOBX ᴮᴱ",
    "country": "BE",
    "type": "live",
    "source": "xtream"
  },
  {
    "tvgId": "GOBX",
    "name": "####### GOBX ᴿᴬᵂ #######",
    "originalName": "####### GOBX ᴿᴬᵂ #######",
    "url": "http://cf.business-cdn-8k.com/cf9b10a37c7c/f4bb9ed47c/1353164.ts",
    "logo": "",
    "category": "Ar| Gobx ᴮᴱ",
    "originalCategory": "AR| GOBX ᴮᴱ",
    "country": "",
    "type": "live",
    "source": "xtream"
  },
  {
    "tvgId": "GOBXMBC1.be",
    "name": "GOBX MBC 1 ᴿᴬᵂ",
    "originalName": "BE: GOBX MBC 1 ᴿᴬᵂ",
    "url": "http://cf.business-cdn-8k.com/cf9b10a37c7c/f4bb9ed47c/1353163.ts",
    "logo": "http://photo-tmdb.com/stalker_portal/misc/logos/320/13334.jpg?59189",
    "category": "Ar| Gobx ᴮᴱ",
    "originalCategory": "AR| GOBX ᴮᴱ",
    "country": "BE",
    "type": "live",
    "source": "xtream"
  },
  {
    "tvgId": "GOBXMBC2.be",
    "name": "GOBX MBC 2 ᴿᴬᵂ",
    "originalName": "BE: GOBX MBC 2 ᴿᴬᵂ",
    "url": "http://cf.business-cdn-8k.com/cf9b10a37c7c/f4bb9ed47c/1353162.ts",
    "logo": "http://photo-tmdb.com/stalker_portal/misc/logos/320/13334.jpg?59189",
    "category": "Ar| Gobx ᴮᴱ",
    "originalCategory": "AR| GOBX ᴮᴱ",
    "country": "BE",
    "type": "live",
    "source": "xtream"
  },
  {
    "tvgId": "GOBXMBC3.be",
    "name": "GOBX MBC 3 ᴿᴬᵂ",
    "originalName": "BE: GOBX MBC 3 ᴿᴬᵂ",
    "url": "http://cf.business-cdn-8k.com/cf9b10a37c7c/f4bb9ed47c/1353161.ts",
    "logo": "http://photo-tmdb.com/stalker_portal/misc/logos/320/13334.jpg?59189",
    "category": "Ar| Gobx ᴮᴱ",
    "originalCategory": "AR| GOBX ᴮᴱ",
    "country": "BE",
    "type": "live",
    "source": "xtream"
  },
  {
    "tvgId": "GOBXMBC4.be",
    "name": "GOBX MBC 4 ᴿᴬᵂ",
    "originalName": "BE: GOBX MBC 4 ᴿᴬᵂ",
    "url": "http://cf.business-cdn-8k.com/cf9b10a37c7c/f4bb9ed47c/1353160.ts",
    "logo": "http://photo-tmdb.com/stalker_portal/misc/logos/320/13334.jpg?59189",
    "category": "Ar| Gobx ᴮᴱ",
    "originalCategory": "AR| GOBX ᴮᴱ",
    "country": "BE",
    "type": "live",
    "source": "xtream"
  },
  {
    "tvgId": "GOBXMBC5.be",
    "name": "GOBX MBC 5 ᴿᴬᵂ",
    "originalName": "BE: GOBX MBC 5 ᴿᴬᵂ",
    "url": "http://cf.business-cdn-8k.com/cf9b10a37c7c/f4bb9ed47c/1353159.ts",
    "logo": "http://photo-tmdb.com/stalker_portal/misc/logos/320/13334.jpg?59189",
    "category": "Ar| Gobx ᴮᴱ",
    "originalCategory": "AR| GOBX ᴮᴱ",
    "country": "BE",
    "type": "live",
    "source": "xtream"
  },
  {
    "tvgId": "GOBXMBCDRAMA.be",
    "name": "GOBX MBC DRAMA ᴿᴬᵂ",
    "originalName": "BE: GOBX MBC DRAMA ᴿᴬᵂ",
    "url": "http://cf.business-cdn-8k.com/cf9b10a37c7c/f4bb9ed47c/1353158.ts",
    "logo": "http://photo-tmdb.com/stalker_portal/misc/logos/320/13334.jpg?59189",
    "category": "Ar| Gobx ᴮᴱ",
    "originalCategory": "AR| GOBX ᴮᴱ",
    "country": "BE",
    "type": "live",
    "source": "xtream"
  },
  {
    "tvgId": "GOBXMBCACTION.be",
    "name": "GOBX MBC ACTION ᴿᴬᵂ",
    "originalName": "BE: GOBX MBC ACTION ᴿᴬᵂ",
    "url": "http://cf.business-cdn-8k.com/cf9b10a37c7c/f4bb9ed47c/1353157.ts",
    "logo": "http://photo-tmdb.com/stalker_portal/misc/logos/320/13334.jpg?59189",
    "category": "Ar| Gobx ᴮᴱ",
    "originalCategory": "AR| GOBX ᴮᴱ",
    "country": "BE",
    "type": "live",
    "source": "xtream"
  },
  {
    "tvgId": "GOBXMBCMASR1.be",
    "name": "GOBX MBC MASR 1 ᴿᴬᵂ",
    "originalName": "BE: GOBX MBC MASR 1 ᴿᴬᵂ",
    "url": "http://cf.business-cdn-8k.com/cf9b10a37c7c/f4bb9ed47c/1353156.ts",
    "logo": "http://photo-tmdb.com/stalker_portal/misc/logos/320/13334.jpg?59189",
    "category": "Ar| Gobx ᴮᴱ",
    "originalCategory": "AR| GOBX ᴮᴱ",
    "country": "BE",
    "type": "live",
    "source": "xtream"
  },
  {
    "tvgId": "GOBXMBCMASR2.be",
    "name": "GOBX MBC MASR 2 ᴿᴬᵂ",
    "originalName": "BE: GOBX MBC MASR 2 ᴿᴬᵂ",
    "url": "http://cf.business-cdn-8k.com/cf9b10a37c7c/f4bb9ed47c/1353155.ts",
    "logo": "http://photo-tmdb.com/stalker_portal/misc/logos/320/13334.jpg?59189",
    "category": "Ar| Gobx ᴮᴱ",
    "originalCategory": "AR| GOBX ᴮᴱ",
    "country": "BE",
    "type": "live",
    "source": "xtream"
  },
  {
    "tvgId": "GOBXMBCIRAQ.be",
    "name": "GOBX MBC IRAQ ᴿᴬᵂ",
    "originalName": "BE: GOBX MBC IRAQ ᴿᴬᵂ",
    "url": "http://cf.business-cdn-8k.com/cf9b10a37c7c/f4bb9ed47c/1353154.ts",
    "logo": "http://photo-tmdb.com/stalker_portal/misc/logos/320/13334.jpg?59189",
    "category": "Ar| Gobx ᴮᴱ",
    "originalCategory": "AR| GOBX ᴮᴱ",
    "country": "BE",
    "type": "live",
    "source": "xtream"
  },
  {
    "tvgId": "GOBXMBCDRAMA.be",
    "name": "GOBX MBC DRAMA+ ᴿᴬᵂ",
    "originalName": "BE: GOBX MBC DRAMA+ ᴿᴬᵂ",
    "url": "http://cf.business-cdn-8k.com/cf9b10a37c7c/f4bb9ed47c/1353153.ts",
    "logo": "http://photo-tmdb.com/stalker_portal/misc/logos/320/13334.jpg?59189",
    "category": "Ar| Gobx ᴮᴱ",
    "originalCategory": "AR| GOBX ᴮᴱ",
    "country": "BE",
    "type": "live",
    "source": "xtream"
  },
  {
    "tvgId": "GOBXMBCVARIETY.be",
    "name": "GOBX MBC VARIETY ᴿᴬᵂ",
    "originalName": "BE: GOBX MBC VARIETY ᴿᴬᵂ",
    "url": "http://cf.business-cdn-8k.com/cf9b10a37c7c/f4bb9ed47c/1353152.ts",
    "logo": "http://photo-tmdb.com/stalker_portal/misc/logos/320/13334.jpg?59189",
    "category": "Ar| Gobx ᴮᴱ",
    "originalCategory": "AR| GOBX ᴮᴱ",
    "country": "BE",
    "type": "live",
    "source": "xtream"
  },
  {
    "tvgId": "GOBXMBCBOLLYWOOD.be",
    "name": "GOBX MBC BOLLYWOOD ᴿᴬᵂ",
    "originalName": "BE: GOBX MBC BOLLYWOOD ᴿᴬᵂ",
    "url": "http://cf.business-cdn-8k.com/cf9b10a37c7c/f4bb9ed47c/1353151.ts",
    "logo": "http://photo-tmdb.com/stalker_portal/misc/logos/320/13334.jpg?59189",
    "category": "Ar| Gobx ᴮᴱ",
    "originalCategory": "AR| GOBX ᴮᴱ",
    "country": "BE",
    "type": "live",
    "source": "xtream"
  }
]